Huffman_Architecture/code_size_generator/code_size_sorting2.v
// Uses odd-even transposition sort for parallel computing
`timescale 1ns/1ps // For testbench, comment out later bhaijaan

module code_size_sorting2 #(
    parameter SYMBOLS = 16,
    parameter CODE_SIZE_WIDTH = 5,
    parameter SYMBOL_ID_WIDTH = 4  // log2(16) = 4
)(
    input wire clk,
    input wire reset,
    input wire enable,
    input wire [SYMBOLS*CODE_SIZE_WIDTH-1:0] code_size_flat,
    input wire [SYMBOLS*SYMBOL_ID_WIDTH-1:0] symbol_id_flat,
    output reg [SYMBOLS*CODE_SIZE_WIDTH-1:0] sorted_code_size_flat,
    output reg [SYMBOLS*SYMBOL_ID_WIDTH-1:0] sorted_symbol_id_flat,
    output reg done
);

    reg [CODE_SIZE_WIDTH-1:0] code_size_array [0:SYMBOLS-1];
    reg [SYMBOL_ID_WIDTH-1:0] symbol_id_array [0:SYMBOLS-1];

    reg [CODE_SIZE_WIDTH-1:0] temp_code_size [0:SYMBOLS-1];
    reg [SYMBOL_ID_WIDTH-1:0] temp_symbol_id [0:SYMBOLS-1];

    integer i, pass, j;
    reg [CODE_SIZE_WIDTH-1:0] temp_cs;
    reg [SYMBOL_ID_WIDTH-1:0] temp_id;

    // FSM states
    reg [3:0] pass_count;
    reg sorting;
    reg stage1_done;
    reg stage2_done;

    // Stage 1: Capture input arrays
    always @(posedge clk) begin
        if (reset) begin
            for (i = 0; i < SYMBOLS; i = i + 1) begin
                code_size_array[i] <= 0;
                symbol_id_array[i] <= 0;
            end
            stage1_done <= 0;
        end else if (enable) begin
            for (i = 0; i < SYMBOLS; i = i + 1) begin
                code_size_array[i] <= code_size_flat[i*CODE_SIZE_WIDTH +: CODE_SIZE_WIDTH];
                symbol_id_array[i] <= symbol_id_flat[i*SYMBOL_ID_WIDTH +: SYMBOL_ID_WIDTH];
            end
            stage1_done <= 1;
        end else begin
            stage1_done <= 0;
        end
    end

    // Stage 2: Sorting using FSM and odd-even transposition
    always @(posedge clk) begin
        if (reset) begin
            pass_count <= 0;
            sorting <= 0;
            stage2_done <= 0;
        end else if (stage1_done && !sorting) begin
            // Copy input to temporary arrays
            for (i = 0; i < SYMBOLS; i = i + 1) begin
                temp_code_size[i] <= code_size_array[i];
                temp_symbol_id[i] <= symbol_id_array[i];
            end
            sorting <= 1;
            pass_count <= 0;
            stage2_done <= 0;
        end else if (sorting) begin
            for (j = pass_count[0]; j < SYMBOLS - 1; j = j + 2) begin
                if (temp_code_size[j] > temp_code_size[j+1]) begin
                    // Swap code sizes
                    temp_cs = temp_code_size[j];
                    temp_code_size[j] <= temp_code_size[j+1];
                    temp_code_size[j+1] <= temp_cs;

                    // Swap symbol IDs
                    temp_id = temp_symbol_id[j];
                    temp_symbol_id[j] <= temp_symbol_id[j+1];
                    temp_symbol_id[j+1] <= temp_id;
                end
            end

            if (pass_count == SYMBOLS - 1) begin
                sorting <= 0;
                stage2_done <= 1;
            end else begin
                pass_count <= pass_count + 1;
            end
        end
    end

    // Stage 3: Output flattened sorted results
    always @(posedge clk) begin
        if (reset) begin
            sorted_code_size_flat <= 0;
            sorted_symbol_id_flat <= 0;
            done <= 0;
        end else if (stage2_done) begin
            for (i = 0; i < SYMBOLS; i = i + 1) begin
                sorted_code_size_flat[i*CODE_SIZE_WIDTH +: CODE_SIZE_WIDTH] <= temp_code_size[i];
                sorted_symbol_id_flat[i*SYMBOL_ID_WIDTH +: SYMBOL_ID_WIDTH] <= temp_symbol_id[i];
            end
            done <= 1;
        end else begin
            done <= 0;
        end
    end

endmodule

Huffman_Architecture/code_size_generator/tb_code_size_sorting_parallel.v
`timescale 1ns/1ps

module tb_code_size_sorting_parallel;

    parameter SYMBOLS = 16;
    parameter CODE_SIZE_WIDTH = 5;
    parameter SYMBOL_ID_WIDTH = 4;

    reg clk;
    reg reset;
    reg enable;
    reg [SYMBOLS*CODE_SIZE_WIDTH-1:0] code_size_flat;
    reg [SYMBOLS*SYMBOL_ID_WIDTH-1:0] symbol_id_flat;
    wire [SYMBOLS*CODE_SIZE_WIDTH-1:0] sorted_code_size_flat;
    wire [SYMBOLS*SYMBOL_ID_WIDTH-1:0] sorted_symbol_id_flat;
    wire done;

    code_size_sorting2 #(
        .SYMBOLS(SYMBOLS),
        .CODE_SIZE_WIDTH(CODE_SIZE_WIDTH),
        .SYMBOL_ID_WIDTH(SYMBOL_ID_WIDTH)
    ) uut (
        .clk(clk),
        .reset(reset),
        .enable(enable),
        .code_size_flat(code_size_flat),
        .symbol_id_flat(symbol_id_flat),
        .sorted_code_size_flat(sorted_code_size_flat),
        .sorted_symbol_id_flat(sorted_symbol_id_flat),
        .done(done)
    );

    // Clock generation
    initial clk = 0;
    always #5 clk = ~clk;

    integer i;
    reg [CODE_SIZE_WIDTH-1:0] sizes [0:SYMBOLS-1];
    reg [SYMBOL_ID_WIDTH-1:0] ids [0:SYMBOLS-1];

    initial begin
        $dumpfile("wave.vcd");
        $dumpvars(0, tb_code_size_sorting_parallel);

        // Initialize signals
        reset = 1;
        enable = 0;
        code_size_flat = 0;
        symbol_id_flat = 0;
        #20;

        reset = 0;
        #10;

        // Create unsorted input
        sizes[0] = 10; ids[0] = 4;
        sizes[1] = 3;  ids[1] = 1;
        sizes[2] = 7;  ids[2] = 2;
        sizes[3] = 2;  ids[3] = 6;
        sizes[4] = 15; ids[4] = 0;
        sizes[5] = 8;  ids[5] = 8;
        sizes[6] = 5;  ids[6] = 3;
        sizes[7] = 1;  ids[7] = 9;
        sizes[8] = 14; ids[8] = 10;
        sizes[9] = 6;  ids[9] = 11;
        sizes[10] = 4; ids[10] = 5;
        sizes[11] = 12;ids[11] = 7;
        sizes[12] = 9; ids[12] = 12;
        sizes[13] = 0; ids[13] = 13;
        sizes[14] = 11;ids[14] = 14;
        sizes[15] = 13;ids[15] = 15;

        // Flatten the arrays
        for (i = 0; i < SYMBOLS; i = i + 1) begin
            code_size_flat[i*CODE_SIZE_WIDTH +: CODE_SIZE_WIDTH] = sizes[i];
            symbol_id_flat[i*SYMBOL_ID_WIDTH +: SYMBOL_ID_WIDTH] = ids[i];
        end

        // Trigger input capture
        enable = 1;
        #10;
        enable = 0;

        // Wait until sorting is complete
        wait (done == 1);
        #10;

        $display("Sorted code sizes and IDs:");
        for (i = 0; i < SYMBOLS; i = i + 1) begin
            $display("code_size[%0d] = %0d, symbol_id = %0d",
                i,
                sorted_code_size_flat[i*CODE_SIZE_WIDTH +: CODE_SIZE_WIDTH],
                sorted_symbol_id_flat[i*SYMBOL_ID_WIDTH +: SYMBOL_ID_WIDTH]
            );
        end

        $display("Done signal status: %b", done);

        #10;
        $finish;
    end

endmodule

Huffman_Architecture/code_size_generator/wave.vcd
$date
	Thu Apr 17 10:11:53 2025
$end
$version
	Icarus Verilog
$end
$timescale
	1ps
$end
$scope module tb_code_size_sorting_parallel $end
$var wire 64 ! sorted_symbol_id_flat [63:0] $end
$var wire 80 " sorted_code_size_flat [79:0] $end
$var wire 1 # done $end
$var parameter 32 $ CODE_SIZE_WIDTH $end
$var parameter 32 % SYMBOLS $end
$var parameter 32 & SYMBOL_ID_WIDTH $end
$var reg 1 ' clk $end
$var reg 80 ( code_size_flat [79:0] $end
$var reg 1 ) enable $end
$var reg 1 * reset $end
$var reg 64 + symbol_id_flat [63:0] $end
$var integer 32 , i [31:0] $end
$scope module uut $end
$var wire 1 ' clk $end
$var wire 80 - code_size_flat [79:0] $end
$var wire 1 ) enable $end
$var wire 1 * reset $end
$var wire 64 . symbol_id_flat [63:0] $end
$var parameter 32 / CODE_SIZE_WIDTH $end
$var parameter 32 0 SYMBOLS $end
$var parameter 32 1 SYMBOL_ID_WIDTH $end
$var reg 1 # done $end
$var reg 4 2 pass_count [3:0] $end
$var reg 80 3 sorted_code_size_flat [79:0] $end
$var reg 64 4 sorted_symbol_id_flat [63:0] $end
$var reg 1 5 sorting $end
$var reg 1 6 stage1_done $end
$var reg 1 7 stage2_done $end
$var reg 5 8 temp_cs [4:0] $end
$var reg 4 9 temp_id [3:0] $end
$var integer 32 : i [31:0] $end
$var integer 32 ; j [31:0] $end
$upscope $end
$upscope $end
$enddefinitions $end
$comment Show the parameter values. $end
$dumpall
b100 1
b10000 0
b101 /
b100 &
b10000 %
b101 $
$end
#0
$dumpvars
bx ;
bx :
bx 9
bx 8
x7
x6
x5
bx 4
bx 3
bx 2
b0 .
b0 -
bx ,
b0 +
1*
0)
b0 (
0'
x#
bx "
bx !
$end
#5000
06
07
05
b0 2
0#
b0 !
b0 4
b0 "
b0 3
b10000 :
1'
#10000
0'
#15000
b10000 :
1'
#20000
0'
0*
#25000
1'
#30000
0'
1)
b1111111011011100011101011011101010010011100000000110001000010100 +
b1111111011011100011101011011101010010011100000000110001000010100 .
b1101010110000001001011000010000110011100000100101010000111100010001110001101010 (
b1101010110000001001011000010000110011100000100101010000111100010001110001101010 -
b10000 ,
#35000
16
b10000 :
1'
#40000
0'
0)
#45000
06
15
b10000 :
1'
#50000
0'
#55000
b1 2
b1100 9
b1001 8
b10000 ;
1'
#60000
0'
#65000
b10 2
b111 9
b1100 8
b1111 ;
1'
#70000
0'
#75000
b11 2
b111 9
b1100 8
b10000 ;
1'
#80000
0'
#85000
b100 2
b111 9
b1100 8
b1111 ;
1'
#90000
0'
#95000
b101 2
b1010 9
b1110 8
b10000 ;
1'
#100000
0'
#105000
b110 2
b1010 9
b1110 8
b1111 ;
1'
#110000
0'
#115000
b111 2
b1010 9
b1110 8
b10000 ;
1'
#120000
0'
#125000
b1000 2
b0 9
b1111 8
b1111 ;
1'
#130000
0'
#135000
b1001 2
b0 9
b1111 8
b10000 ;
1'
#140000
0'
#145000
b1010 2
b0 9
b1111 8
b1111 ;
1'
#150000
0'
#155000
b1011 2
b0 9
b1111 8
b10000 ;
1'
#160000
0'
#165000
b1100 2
b110 9
b10 8
b1111 ;
1'
#170000
0'
#175000
b1101 2
b1001 9
b1 8
b10000 ;
1'
#180000
0'
#185000
b1110 2
b1111 ;
1'
#190000
0'
#195000
b1111 2
b10000 ;
1'
#200000
0'
#205000
17
05
b1111 ;
1'
#210000
0'
#215000
1#
b1111011100110101100010110101001001010000011100110001010010000011000100000100000 "
b1111011100110101100010110101001001010000011100110001010010000011000100000100000 3
b101011110111111001001100100000101011001101010001011010011101 !
b101011110111111001001100100000101011001101010001011010011101 4
b10000 :
1'
#220000
0'
#225000
b10000 :
1'
b10000 ,
#230000
0'
#235000
b10000 :
1'
