Huffman_Architecture/frequency_generation_stage/stream_sorter_oets.v
/*module stream_sorter_oets #(
    parameter SYMBOLS = 16,
    parameter DATA_WIDTH = 5,
    parameter SYMBOL_WIDTH = 5
)(
    input  wire clk,
    input  wire reset,

    // Input stream interface
    input  wire [DATA_WIDTH-1:0] data_in,
    input  wire [SYMBOL_WIDTH-1:0]    symbol_in,
    input  wire                       valid_in,
    output reg                        ready_in,

    // Output sorted flat arrays
    output reg [SYMBOLS*DATA_WIDTH-1:0]      sorted_data_flat,
    output reg [SYMBOLS*SYMBOL_WIDTH-1:0]    sorted_symbol_flat,
    output reg                               sorted_done
);

    localparam PAIR_WIDTH = DATA_WIDTH + SYMBOL_WIDTH;
    localparam COUNT_WIDTH = $clog2(SYMBOLS + 1);

    // Buffer to store sorted {code_size, symbol} pairs
    reg [DATA_WIDTH-1:0] code_size_buffer [0:SYMBOLS-1];
    reg [SYMBOL_WIDTH-1:0]    symbol_buffer [0:SYMBOLS-1];
    reg [COUNT_WIDTH-1:0]     input_count;
    reg                       sorting;
    reg [COUNT_WIDTH-1:0]     insert_pos;
    reg [COUNT_WIDTH-1:0]     shift_count;

    // States for insertion sort
    localparam [1:0]
        S_IDLE   = 2'd0,
        S_INSERT = 2'd1,
        S_SHIFT  = 2'd2,
        S_DONE   = 2'd3;

    reg [1:0] state, next_state;

    // Handshake: ready when not shifting or done
    always @(*) begin
        ready_in = (state == S_IDLE || state == S_INSERT) && input_count < SYMBOLS;
    end

    // FSM state transition
    always @(posedge clk or posedge reset) begin
        if (reset) begin
            state <= S_IDLE;
        end else begin
            state <= next_state;
        end
    end

    // Next state logic
    always @(*) begin
        case (state)
            S_IDLE: begin
                if (valid_in && ready_in && input_count < SYMBOLS) begin
                    next_state = S_INSERT;
                end else begin
                    next_state = S_IDLE;
                end
            end
            S_INSERT: begin
                if (insert_pos == input_count || code_size_buffer[insert_pos] >= data_in) begin
                    next_state = S_SHIFT;
                end else begin
                    next_state = S_INSERT;
                end
            end
            S_SHIFT: begin
                if (shift_count == 0) begin
                    if (input_count == SYMBOLS) begin
                        next_state = S_DONE;
                    end else begin
                        next_state = S_IDLE;
                    end
                end else begin
                    next_state = S_SHIFT;
                end
            end
            S_DONE: begin
                next_state = S_DONE; // Stay until reset
            end
            default: next_state = S_IDLE;
        endcase
    end

    // Main logic
    always @(posedge clk or posedge reset) begin
        if (reset) begin
            input_count <= 0;
            sorting <= 0;
            sorted_done <= 0;
            insert_pos <= 0;
            shift_count <= 0;
            for (integer i = 0; i < SYMBOLS; i = i + 1) begin
                code_size_buffer[i] <= 0;
                symbol_buffer[i] <= 0;
            end
            sorted_data_flat <= 0;
            sorted_symbol_flat <= 0;
        end else begin
            case (state)
                S_IDLE: begin
                    if (valid_in && ready_in && input_count < SYMBOLS) begin
                        sorting <= 1;
                        insert_pos <= 0;
                        input_count <= input_count + 1;
                    end
                end
                S_INSERT: begin
                    if (insert_pos < input_count) begin
                        if (code_size_buffer[insert_pos] < data_in) begin
                            insert_pos <= insert_pos + 1;
                        end else begin
                            shift_count <= input_count - insert_pos;
                        end
                    end else begin
                        shift_count <= 0; // Insert at end
                    end
                end
                S_SHIFT: begin
                    if (shift_count > 0) begin
                        // Shift elements to make room
                        for (integer i = input_count - 1; i > insert_pos; i = i - 1) begin
                            code_size_buffer[i] <= code_size_buffer[i-1];
                            symbol_buffer[i] <= symbol_buffer[i-1];
                        end
                        // Insert new data
                        code_size_buffer[insert_pos] <= data_in;
                        symbol_buffer[insert_pos] <= symbol_in;
                        shift_count <= shift_count - 1;
                    end else begin
                        // Insert at end if no shift needed
                        code_size_buffer[insert_pos] <= data_in;
                        symbol_buffer[insert_pos] <= symbol_in;
                        sorting <= (input_count < SYMBOLS);
                    end
                end
                S_DONE: begin
                    sorted_done <= 1;
                    // Flatten outputs
                    for (integer i = 0; i < SYMBOLS; i = i + 1) begin
                        sorted_data_flat[i*DATA_WIDTH +: DATA_WIDTH] <= code_size_buffer[i];
                        sorted_symbol_flat[i*SYMBOL_WIDTH +: SYMBOL_WIDTH] <= symbol_buffer[i];
                    end
                end
            endcase
        end
    end

endmodule*/



module stream_sorter_oets #(
    parameter SYMBOLS = 16,
    parameter FREQ_WIDTH = 32,
    parameter SYMBOL_WIDTH = 5
)(
    input wire clk,
    input wire reset,
    input wire [SYMBOL_WIDTH-1:0] symbol_in,
    input wire valid_in,
    output wire ready_in,
    output reg [SYMBOLS*FREQ_WIDTH-1:0] sorted_frequencies_flat,
    output reg [SYMBOLS*SYMBOL_WIDTH-1:0] sorted_symbol_flat,
    output reg sorted_done
);
    // Total width for a frequency-symbol pair.
    localparam PAIR_WIDTH = FREQ_WIDTH + SYMBOL_WIDTH;

    // Buffer stores each element as { frequency, symbol }.
    reg [PAIR_WIDTH-1:0] buffer [0:SYMBOLS-1];
    // Combinational next-state buffer.
    reg [PAIR_WIDTH-1:0] buffer_next [0:SYMBOLS-1];
    // Temporary register for swapping.
    reg [PAIR_WIDTH-1:0] temp;
    // Counter for input symbols and total passes.
    reg [4:0] input_count; // Tracks actual number of valid inputs
    reg [5:0] pass_count;  // Tracks sorting passes
    reg [5:0] idle_count;  // Counts cycles with no new input
    integer i;
    
    // Always ready for an update.
    assign ready_in = 1;
    
    // Helper function: returns the lower SYMBOL_WIDTH bits of an integer.
    function [SYMBOL_WIDTH-1:0] lower_bits;
        //input integer value;
        input [31:0] value;
        begin
            lower_bits = value & ((1 << SYMBOL_WIDTH) - 1);
        end
    endfunction

    // Combinational block: compute next state by copying current state, 
    // updating the frequency (if valid_in is high) and performing one 
    // odd–even pass for ascending order.
    always @* begin
        // Start by copying the current state.
        for (i = 0; i < SYMBOLS; i = i + 1)
            buffer_next[i] = buffer[i];
            
        // Update: If valid, increment the frequency for the matching symbol.
        if (valid_in) begin
            for (i = 0; i < SYMBOLS; i = i + 1) begin
                if (buffer_next[i][SYMBOL_WIDTH-1:0] == symbol_in)
                    buffer_next[i][PAIR_WIDTH-1:SYMBOL_WIDTH] = 
                        buffer_next[i][PAIR_WIDTH-1:SYMBOL_WIDTH] + 1;
            end
        end
        
        // Odd phase: compare pairs (0,1), (2,3), ... and swap if left frequency > right.
        for (i = 0; i < SYMBOLS-1; i = i + 2) begin
            if (buffer_next[i][PAIR_WIDTH-1:SYMBOL_WIDTH] > buffer_next[i+1][PAIR_WIDTH-1:SYMBOL_WIDTH]) begin
                temp = buffer_next[i];
                buffer_next[i] = buffer_next[i+1];
                buffer_next[i+1] = temp;
            end
        end
        
        // Even phase: compare pairs (1,2), (3,4), ... and swap if left frequency > right.
        for (i = 1; i < SYMBOLS-1; i = i + 2) begin
            if (buffer_next[i][PAIR_WIDTH-1:SYMBOL_WIDTH] > buffer_next[i+1][PAIR_WIDTH-1:SYMBOL_WIDTH]) begin
                temp = buffer_next[i];
                buffer_next[i] = buffer_next[i+1];
                buffer_next[i+1] = temp;
            end
        end
    end

    // Sequential block: update the buffer and counters on each posedge of clk.
    always @(posedge clk or posedge reset) begin
        if (reset) begin
            // Initialize: frequency=0, symbol = lower bits of the index.
            for (i = 0; i < SYMBOLS; i = i + 1)
                buffer[i] <= { {FREQ_WIDTH{1'b0}}, lower_bits(i) };
            input_count <= 0;
            pass_count <= 0;
            idle_count <= 0;
            sorted_done <= 0;
        end else begin
            for (i = 0; i < SYMBOLS; i = i + 1)
                buffer[i] <= buffer_next[i];
            if (valid_in) begin
                input_count <= input_count + 1;
                idle_count <= 0; // Reset idle count when new input arrives
            end else begin
                idle_count <= idle_count + 1; // Increment idle count when no input
            end
            pass_count <= pass_count + 1;
            // Set sorted_done when no new input for SYMBOLS + 4 cycles after last input
            if (idle_count >= SYMBOLS + 4 && input_count > 0) begin
                sorted_done <= 1;
            end
        end
    end

    // Continuously drive the flattened outputs.
    always @* begin
        for (i = 0; i < SYMBOLS; i = i + 1) begin
            sorted_frequencies_flat[i*FREQ_WIDTH +: FREQ_WIDTH] = 
                buffer[i][PAIR_WIDTH-1:SYMBOL_WIDTH];
            sorted_symbol_flat[i*SYMBOL_WIDTH +: SYMBOL_WIDTH] = 
                buffer[i][SYMBOL_WIDTH-1:0];
        end
    end

endmodule

Huffman_Architecture/frequency_generation_stage/frequency_generation_stage.v
module frequency_generation_stage #(
    parameter SYMBOL_WIDTH = 5,    // Width of input symbols (0-15)
    parameter FREQ_WIDTH = 32,     // Width of frequency counters
    parameter NUM_CELLS = 16       // Number of unique symbols
) (
    input  wire clk,
    input  wire reset,
    input  wire [SYMBOL_WIDTH-1:0] symbol_in,  // Input symbol
    input  wire valid_in,                      // Input valid signal
    output wire ready_in,                      // Ready to accept input
    output wire [NUM_CELLS*FREQ_WIDTH-1:0] sorted_frequencies,  // Sorted frequencies
    output wire [NUM_CELLS*SYMBOL_WIDTH-1:0] sorted_symbols,    // Sorted symbols
    output wire sorted_done                    // Sorting complete signal
);

    // Instantiate the updated stream_sorter_oets module
    stream_sorter_oets #(
        .SYMBOLS(NUM_CELLS),
        .FREQ_WIDTH(FREQ_WIDTH),
        .SYMBOL_WIDTH(SYMBOL_WIDTH)
    ) sorter_inst (
        .clk(clk),
        .reset(reset),
        .symbol_in(symbol_in),
        .valid_in(valid_in),
        .ready_in(ready_in),
        .sorted_frequencies_flat(sorted_frequencies),
        .sorted_symbol_flat(sorted_symbols),
        .sorted_done(sorted_done)
    );

endmodule

Huffman_Architecture/frequency_generation_stage/tb_frequency_generation_stage.v
`timescale 1ns/1ps

module tb_frequency_generation_stage;

    //----------------------------------------------------------------------------
    // Dump for GTKWave
    //----------------------------------------------------------------------------
    initial begin
        // Name of the VCD file
        $dumpfile("frequency_generation_stage.vcd");
        // Dump everything in this module hierarchy
        $dumpvars(0, tb_frequency_generation_stage);
    end

    // Parameters
    parameter SYMBOL_WIDTH = 5;
    parameter FREQ_WIDTH   = 32;
    parameter NUM_CELLS    = 16;
    parameter CLK_PERIOD   = 10;

    // Signals
    reg clk;
    reg reset;
    reg [SYMBOL_WIDTH-1:0] symbol_in;
    reg valid_in;
    wire ready_in;
    wire [NUM_CELLS*FREQ_WIDTH-1:0]   sorted_frequencies;
    wire [NUM_CELLS*SYMBOL_WIDTH-1:0] sorted_symbols;
    wire sorted_done;

    // Instantiate the DUT
    frequency_generation_stage #(
        .SYMBOL_WIDTH(SYMBOL_WIDTH),
        .FREQ_WIDTH(FREQ_WIDTH),
        .NUM_CELLS(NUM_CELLS)
    ) dut (
        .clk(clk),
        .reset(reset),
        .symbol_in(symbol_in),
        .valid_in(valid_in),
        .ready_in(ready_in),
        .sorted_frequencies(sorted_frequencies),
        .sorted_symbols(sorted_symbols),
        .sorted_done(sorted_done)
    );

    // Clock generation
    always #(CLK_PERIOD/2) clk = ~clk;

    // Test stimulus
    initial begin
        // Initialize signals
        clk       = 0;
        reset     = 1;
        valid_in  = 0;
        symbol_in = 0;
        #20;
        reset = 0;
        #10;

        // mississippi sequence
        symbol_in = 0; valid_in = 1; #10; valid_in = 0; #10; // m
        symbol_in = 1; valid_in = 1; #10; valid_in = 0; #10; // i
        symbol_in = 2; valid_in = 1; #10; valid_in = 0; #10; // s
        symbol_in = 2; valid_in = 1; #10; valid_in = 0; #10; // s
        symbol_in = 1; valid_in = 1; #10; valid_in = 0; #10; // i
        symbol_in = 2; valid_in = 1; #10; valid_in = 0; #10; // s
        symbol_in = 2; valid_in = 1; #10; valid_in = 0; #10; // s
        symbol_in = 1; valid_in = 1; #10; valid_in = 0; #10; // i
        symbol_in = 3; valid_in = 1; #10; valid_in = 0; #10; // p
        symbol_in = 3; valid_in = 1; #10; valid_in = 0; #10; // p
        symbol_in = 1; valid_in = 1; #10; valid_in = 0; #10; // i

        // Wait for sorting to complete
        wait (sorted_done);
        #50;

        // Display results
        $display("Sorting completed. Sorted Symbols and Frequencies:");
        for (integer i = 0; i < NUM_CELLS; i = i + 1) begin
            $display("Cell %2d: Symbol=%2d, Freq=%d",
                     i,
                     sorted_symbols[i*SYMBOL_WIDTH +: SYMBOL_WIDTH],
                     sorted_frequencies[i*FREQ_WIDTH +: FREQ_WIDTH]);
        end
        $finish;
    end

    // Monitor
    initial begin
        $monitor("Time=%0t reset=%b valid_in=%b ready_in=%b symbol_in=%d sorted_done=%b",
                 $time, reset, valid_in, ready_in, symbol_in, sorted_done);
    end

endmodule

Huffman_Architecture/frequency_generation_stage/frequency_generation_stage.vcd
$date
	Thu Apr 17 09:56:46 2025
$end
$version
	Icarus Verilog
$end
$timescale
	1ps
$end
$scope module tb_frequency_generation_stage $end
$var wire 1 ! ready_in $end
$var wire 80 " sorted_symbols [79:0] $end
$var wire 512 # sorted_frequencies [511:0] $end
$var wire 1 $ sorted_done $end
$var parameter 32 % CLK_PERIOD $end
$var parameter 32 & FREQ_WIDTH $end
$var parameter 32 ' NUM_CELLS $end
$var parameter 32 ( SYMBOL_WIDTH $end
$var reg 1 ) clk $end
$var reg 1 * reset $end
$var reg 5 + symbol_in [4:0] $end
$var reg 1 , valid_in $end
$scope module dut $end
$var wire 1 ) clk $end
$var wire 1 ! ready_in $end
$var wire 1 * reset $end
$var wire 5 - symbol_in [4:0] $end
$var wire 1 , valid_in $end
$var wire 80 . sorted_symbols [79:0] $end
$var wire 512 / sorted_frequencies [511:0] $end
$var wire 1 $ sorted_done $end
$var parameter 32 0 FREQ_WIDTH $end
$var parameter 32 1 NUM_CELLS $end
$var parameter 32 2 SYMBOL_WIDTH $end
$scope module sorter_inst $end
$var wire 1 ) clk $end
$var wire 1 ! ready_in $end
$var wire 1 * reset $end
$var wire 5 3 symbol_in [4:0] $end
$var wire 1 , valid_in $end
$var parameter 32 4 FREQ_WIDTH $end
$var parameter 33 5 PAIR_WIDTH $end
$var parameter 32 6 SYMBOLS $end
$var parameter 32 7 SYMBOL_WIDTH $end
$var reg 6 8 idle_count [5:0] $end
$var reg 5 9 input_count [4:0] $end
$var reg 6 : pass_count [5:0] $end
$var reg 1 $ sorted_done $end
$var reg 512 ; sorted_frequencies_flat [511:0] $end
$var reg 80 < sorted_symbol_flat [79:0] $end
$var reg 37 = temp [36:0] $end
$var integer 32 > i [31:0] $end
$scope function lower_bits $end
$var reg 32 ? value [31:0] $end
$upscope $end
$upscope $end
$upscope $end
$scope begin $ivl_for_loop0 $end
$var integer 32 @ i [31:0] $end
$upscope $end
$upscope $end
$enddefinitions $end
$comment Show the parameter values. $end
$dumpall
b101 7
b10000 6
b100101 5
b100000 4
b101 2
b10000 1
b100000 0
b101 (
b10000 '
b100000 &
b1010 %
$end
#0
$dumpvars
bx @
b1111 ?
b10000 >
bx =
b1111011100110101100010110101001001010000011100110001010010000011000100000100000 <
b0 ;
b0 :
b0 9
b0 8
b0 3
b0 /
b1111011100110101100010110101001001010000011100110001010010000011000100000100000 .
b0 -
0,
b0 +
1*
0)
0$
b0 #
b1111011100110101100010110101001001010000011100110001010010000011000100000100000 "
1!
$end
#5000
b1111 ?
b10000 >
1)
#10000
0)
#15000
b1111 ?
b10000 >
1)
#20000
0)
0*
#25000
b1 :
b1 8
b10000 >
1)
#30000
b100000 =
b1111 >
0)
1,
#35000
b10000000000000000000000000000000000000000000000000000000000000000 #
b10000000000000000000000000000000000000000000000000000000000000000 /
b10000000000000000000000000000000000000000000000000000000000000000 ;
b1111011100110101100010110101001001010000011100110001010010000011000000001000001 "
b1111011100110101100010110101001001010000011100110001010010000011000000001000001 .
b1111011100110101100010110101001001010000011100110001010010000011000000001000001 <
b1000000 =
b10 :
b0 8
b1 9
b10000 >
1)
#40000
b100000 =
b1111 >
0)
0,
#45000
b1111011100110101100010110101001001010000011100110001010000000100000110001000001 "
b1111011100110101100010110101001001010000011100110001010000000100000110001000001 .
b1111011100110101100010110101001001010000011100110001010000000100000110001000001 <
b100000000000000000000000000000000000000000000000000000000000000000000000000000000000000000000000000000000000000000000000000000000 #
b100000000000000000000000000000000000000000000000000000000000000000000000000000000000000000000000000000000000000000000000000000000 /
b100000000000000000000000000000000000000000000000000000000000000000000000000000000000000000000000000000000000000000000000000000000 ;
b11 :
b1 8
b10000 >
1)
#50000
b100000 =
b1111 >
0)
1,
b1 +
b1 -
b1 3
#55000
b1000000000000000000000000000000000000000000000000000000000000000000000000000000000000000000000000000000000000000000000000000000010000000000000000000000000000000000000000000000000000000000000000 #
b1000000000000000000000000000000000000000000000000000000000000000000000000000000000000000000000000000000000000000000000000000000010000000000000000000000000000000000000000000000000000000000000000 /
b1000000000000000000000000000000000000000000000000000000000000000000000000000000000000000000000000000000000000000000000000000000010000000000000000000000000000000000000000000000000000000000000000 ;
b1111011100110101100010110101001001010000011100000001100010100100000010001100010 "
b1111011100110101100010110101001001010000011100000001100010100100000010001100010 .
b1111011100110101100010110101001001010000011100000001100010100100000010001100010 <
b100000 =
b100 :
b0 8
b10 9
b10000 >
1)
#60000
b100000 =
b1111 >
0)
0,
#65000
b1111011100110101100010110101001001000000100000111001100000100101001000001100010 "
b1111011100110101100010110101001001000000100000111001100000100101001000001100010 .
b1111011100110101100010110101001001000000100000111001100000100101001000001100010 <
b10000000000000000000000000000000000000000000000000000000000000000000000000000000000000000000000000000000000000000000000000000000100000000000000000000000000000000000000000000000000000000000000000000000000000000000000000000000000000000000000000000000000000000 #
b10000000000000000000000000000000000000000000000000000000000000000000000000000000000000000000000000000000000000000000000000000000100000000000000000000000000000000000000000000000000000000000000000000000000000000000000000000000000000000000000000000000000000000 /
b10000000000000000000000000000000000000000000000000000000000000000000000000000000000000000000000000000000000000000000000000000000100000000000000000000000000000000000000000000000000000000000000000000000000000000000000000000000000000000000000000000000000000000 ;
b100000 =
b101 :
b1 8
b10000 >
1)
#70000
b100000 =
b1111 >
0)
1,
b10 +
b10 -
b10 3
#75000
b100000000000000000000000000000000000000000000000000000000000000000000000000000000000000000000000000000000000000000000000000000001000000000000000000000000000000000000000000000000000000000000000000000000000000000000000000000000000000000000000000000000000000010000000000000000000000000000000000000000000000000000000000000000 #
b100000000000000000000000000000000000000000000000000000000000000000000000000000000000000000000000000000000000000000000000000000001000000000000000000000000000000000000000000000000000000000000000000000000000000000000000000000000000000000000000000000000000000010000000000000000000000000000000000000000000000000000000000000000 /
b100000000000000000000000000000000000000000000000000000000000000000000000000000000000000000000000000000000000000000000000000000001000000000000000000000000000000000000000000000000000000000000000000000000000000000000000000000000000000000000000000000000000000010000000000000000000000000000000000000000000000000000000000000000 ;
b1111011100110101100010110000001010010010100000001001110011000101000100010000011 "
b1111011100110101100010110000001010010010100000001001110011000101000100010000011 .
b1111011100110101100010110000001010010010100000001001110011000101000100010000011 <
b100000 =
b110 :
b0 8
b11 9
b10000 >
1)
#80000
b100000 =
b1111 >
0)
0,
#85000
b1111011100110100000011000101101010000010100101000001110001000110001010010000011 "
b1111011100110100000011000101101010000010100101000001110001000110001010010000011 .
b1111011100110100000011000101101010000010100101000001110001000110001010010000011 <
b1000000000000000000000000000000000000000000000000000000000000000000000000000000000000000000000000000000000000000000000000000000010000000000000000000000000000000000000000000000000000000000000000000000000000000000000000000000000000000000000000000000000000000100000000000000000000000000000000000000000000000000000000000000000000000000000000000000000000000000000000000000000000000000000000 #
b1000000000000000000000000000000000000000000000000000000000000000000000000000000000000000000000000000000000000000000000000000000010000000000000000000000000000000000000000000000000000000000000000000000000000000000000000000000000000000000000000000000000000000100000000000000000000000000000000000000000000000000000000000000000000000000000000000000000000000000000000000000000000000000000000 /
b1000000000000000000000000000000000000000000000000000000000000000000000000000000000000000000000000000000000000000000000000000000010000000000000000000000000000000000000000000000000000000000000000000000000000000000000000000000000000000000000000000000000000000100000000000000000000000000000000000000000000000000000000000000000000000000000000000000000000000000000000000000000000000000000000 ;
b100000 =
b111 :
b1 8
b10000 >
1)
#90000
b100000 =
b1111 >
0)
1,
#95000
b1111000000111001101011000000101011010100100100010010000011100110001010010000011 "
b1111000000111001101011000000101011010100100100010010000011100110001010010000011 .
b1111000000111001101011000000101011010100100100010010000011100110001010010000011 <
b10000000000000000000000000000000000000000000000000000000000000000000000000000000000000000000000000000000000000000000000000000000100000000000000000000000000000000000000000000000000000000000000000000000000000000000000000000000000000000000000000000000000000010000000000000000000000000000000000000000000000000000000000000000000000000000000000000000000000000000000000000000000000000000000000000000000000000000000000000000000000000000000000000000000000000 #
b10000000000000000000000000000000000000000000000000000000000000000000000000000000000000000000000000000000000000000000000000000000100000000000000000000000000000000000000000000000000000000000000000000000000000000000000000000000000000000000000000000000000000010000000000000000000000000000000000000000000000000000000000000000000000000000000000000000000000000000000000000000000000000000000000000000000000000000000000000000000000000000000000000000000000000 /
b10000000000000000000000000000000000000000000000000000000000000000000000000000000000000000000000000000000000000000000000000000000100000000000000000000000000000000000000000000000000000000000000000000000000000000000000000000000000000000000000000000000000000010000000000000000000000000000000000000000000000000000000000000000000000000000000000000000000000000000000000000000000000000000000000000000000000000000000000000000000000000000000000000000000000000 ;
b100001 =
b1000 :
b0 8
b100 9
b10000 >
1)
#100000
b100001 =
b1111 >
0)
0,
#105000
b11110111000001011010110001011000100101001001010000011100110001010010000011 "
b11110111000001011010110001011000100101001001010000011100110001010010000011 .
b11110111000001011010110001011000100101001001010000011100110001010010000011 <
b1000000000000000000000000000000000000000000000000000000000000000000000000000000000000000000000001000000000000000000000000000000000000000000000000000000000000000000000000000000000000000000000000000000000000000000000000000000100000000000000000000000000000000000000000000000000000000000000000000000000000000000000000000000000000000000000000000000000000000000000000000000000000000000000000000000000000000000000000000000000000000000000000000000000000000000000000000000000000000000000000 #
b1000000000000000000000000000000000000000000000000000000000000000000000000000000000000000000000001000000000000000000000000000000000000000000000000000000000000000000000000000000000000000000000000000000000000000000000000000000100000000000000000000000000000000000000000000000000000000000000000000000000000000000000000000000000000000000000000000000000000000000000000000000000000000000000000000000000000000000000000000000000000000000000000000000000000000000000000000000000000000000000000 /
b1000000000000000000000000000000000000000000000000000000000000000000000000000000000000000000000001000000000000000000000000000000000000000000000000000000000000000000000000000000000000000000000000000000000000000000000000000000100000000000000000000000000000000000000000000000000000000000000000000000000000000000000000000000000000000000000000000000000000000000000000000000000000000000000000000000000000000000000000000000000000000000000000000000000000000000000000000000000000000000000000 ;
b100001 =
b1001 :
b1 8
b10000 >
1)
#110000
b1000001 =
b1111 >
0)
1,
b1 +
b1 -
b1 3
#115000
b10111101110011010001001100010110101001001010000011100110001010010000011 "
b10111101110011010001001100010110101001001010000011100110001010010000011 .
b10111101110011010001001100010110101001001010000011100110001010010000011 <
b1000000000000000000000000000000100000000000000000000000000000000000000000000000000000000000000000000000000000000000000000000000000000000000000000000000000000001000000000000000000000000000000000000000000000000000000000000000000000000000000000000000000000000000000000000000000000000000000000000000000000000000000000000000000000000000000000000000000000000000000000000000000000000000000000000000000000000000000000000000000000000000000000000000000000000000000000000000000000000000000000 #
b1000000000000000000000000000000100000000000000000000000000000000000000000000000000000000000000000000000000000000000000000000000000000000000000000000000000000001000000000000000000000000000000000000000000000000000000000000000000000000000000000000000000000000000000000000000000000000000000000000000000000000000000000000000000000000000000000000000000000000000000000000000000000000000000000000000000000000000000000000000000000000000000000000000000000000000000000000000000000000000000000 /
b1000000000000000000000000000000100000000000000000000000000000000000000000000000000000000000000000000000000000000000000000000000000000000000000000000000000000001000000000000000000000000000000000000000000000000000000000000000000000000000000000000000000000000000000000000000000000000000000000000000000000000000000000000000000000000000000000000000000000000000000000000000000000000000000000000000000000000000000000000000000000000000000000000000000000000000000000000000000000000000000000 ;
b1000010 =
b1010 :
b0 8
b101 9
b10000 >
1)
#120000
b1000010 =
b1111 >
0)
0,
#125000
b1000000111100010011100110101100010110101001001010000011100110001010010000011 "
b1000000111100010011100110101100010110101001001010000011100110001010010000011 .
b1000000111100010011100110101100010110101001001010000011100110001010010000011 <
b10000000000000000000000000000000010000000000000000000000000000000000000000000000000000000000000010000000000000000000000000000000000000000000000000000000000000000000000000000000000000000000000000000000000000000000000000000000000000000000000000000000000000000000000000000000000000000000000000000000000000000000000000000000000000000000000000000000000000000000000000000000000000000000000000000000000000000000000000000000000000000000000000000000000000000000000000000000000000000000000000 #
b10000000000000000000000000000000010000000000000000000000000000000000000000000000000000000000000010000000000000000000000000000000000000000000000000000000000000000000000000000000000000000000000000000000000000000000000000000000000000000000000000000000000000000000000000000000000000000000000000000000000000000000000000000000000000000000000000000000000000000000000000000000000000000000000000000000000000000000000000000000000000000000000000000000000000000000000000000000000000000000000000 /
b10000000000000000000000000000000010000000000000000000000000000000000000000000000000000000000000010000000000000000000000000000000000000000000000000000000000000000000000000000000000000000000000000000000000000000000000000000000000000000000000000000000000000000000000000000000000000000000000000000000000000000000000000000000000000000000000000000000000000000000000000000000000000000000000000000000000000000000000000000000000000000000000000000000000000000000000000000000000000000000000000 ;
b1011 :
b1 8
b10000 >
1)
#130000
b1100010 =
b1111 >
0)
1,
b10 +
b10 -
b10 3
#135000
b1000100000001111011100110101100010110101001001010000011100110001010010000011 "
b1000100000001111011100110101100010110101001001010000011100110001010010000011 .
b1000100000001111011100110101100010110101001001010000011100110001010010000011 <
b10000000000000000000000000000000110000000000000000000000000000000100000000000000000000000000000000000000000000000000000000000000000000000000000000000000000000000000000000000000000000000000000000000000000000000000000000000000000000000000000000000000000000000000000000000000000000000000000000000000000000000000000000000000000000000000000000000000000000000000000000000000000000000000000000000000000000000000000000000000000000000000000000000000000000000000000000000000000000000000000000 #
b10000000000000000000000000000000110000000000000000000000000000000100000000000000000000000000000000000000000000000000000000000000000000000000000000000000000000000000000000000000000000000000000000000000000000000000000000000000000000000000000000000000000000000000000000000000000000000000000000000000000000000000000000000000000000000000000000000000000000000000000000000000000000000000000000000000000000000000000000000000000000000000000000000000000000000000000000000000000000000000000000 /
b10000000000000000000000000000000110000000000000000000000000000000100000000000000000000000000000000000000000000000000000000000000000000000000000000000000000000000000000000000000000000000000000000000000000000000000000000000000000000000000000000000000000000000000000000000000000000000000000000000000000000000000000000000000000000000000000000000000000000000000000000000000000000000000000000000000000000000000000000000000000000000000000000000000000000000000000000000000000000000000000000 ;
b10000010 =
b1100 :
b0 8
b110 9
b10000 >
1)
#140000
b1100010 =
b1111 >
0)
0,
#145000
b10000010000001111011100110101100010110101001001010000011100110001010010000011 "
b10000010000001111011100110101100010110101001001010000011100110001010010000011 .
b10000010000001111011100110101100010110101001001010000011100110001010010000011 <
b11000000000000000000000000000000100000000000000000000000000000000100000000000000000000000000000000000000000000000000000000000000000000000000000000000000000000000000000000000000000000000000000000000000000000000000000000000000000000000000000000000000000000000000000000000000000000000000000000000000000000000000000000000000000000000000000000000000000000000000000000000000000000000000000000000000000000000000000000000000000000000000000000000000000000000000000000000000000000000000000000 #
b11000000000000000000000000000000100000000000000000000000000000000100000000000000000000000000000000000000000000000000000000000000000000000000000000000000000000000000000000000000000000000000000000000000000000000000000000000000000000000000000000000000000000000000000000000000000000000000000000000000000000000000000000000000000000000000000000000000000000000000000000000000000000000000000000000000000000000000000000000000000000000000000000000000000000000000000000000000000000000000000000 /
b11000000000000000000000000000000100000000000000000000000000000000100000000000000000000000000000000000000000000000000000000000000000000000000000000000000000000000000000000000000000000000000000000000000000000000000000000000000000000000000000000000000000000000000000000000000000000000000000000000000000000000000000000000000000000000000000000000000000000000000000000000000000000000000000000000000000000000000000000000000000000000000000000000000000000000000000000000000000000000000000000 ;
b1101 :
b1 8
b10000 >
1)
#150000
b1111 >
0)
1,
#155000
b100000000000000000000000000000000100000000000000000000000000000000100000000000000000000000000000000000000000000000000000000000000000000000000000000000000000000000000000000000000000000000000000000000000000000000000000000000000000000000000000000000000000000000000000000000000000000000000000000000000000000000000000000000000000000000000000000000000000000000000000000000000000000000000000000000000000000000000000000000000000000000000000000000000000000000000000000000000000000000000000000 #
b100000000000000000000000000000000100000000000000000000000000000000100000000000000000000000000000000000000000000000000000000000000000000000000000000000000000000000000000000000000000000000000000000000000000000000000000000000000000000000000000000000000000000000000000000000000000000000000000000000000000000000000000000000000000000000000000000000000000000000000000000000000000000000000000000000000000000000000000000000000000000000000000000000000000000000000000000000000000000000000000000 /
b100000000000000000000000000000000100000000000000000000000000000000100000000000000000000000000000000000000000000000000000000000000000000000000000000000000000000000000000000000000000000000000000000000000000000000000000000000000000000000000000000000000000000000000000000000000000000000000000000000000000000000000000000000000000000000000000000000000000000000000000000000000000000000000000000000000000000000000000000000000000000000000000000000000000000000000000000000000000000000000000000 ;
b1110 :
b0 8
b111 9
b10000 >
1)
#160000
b1111 >
0)
0,
#165000
b1111 :
b1 8
b10000 >
1)
#170000
b1111 >
0)
1,
b1 +
b1 -
b1 3
#175000
b100000000000000000000000000000000110000000000000000000000000000000100000000000000000000000000000000000000000000000000000000000000000000000000000000000000000000000000000000000000000000000000000000000000000000000000000000000000000000000000000000000000000000000000000000000000000000000000000000000000000000000000000000000000000000000000000000000000000000000000000000000000000000000000000000000000000000000000000000000000000000000000000000000000000000000000000000000000000000000000000000 #
b100000000000000000000000000000000110000000000000000000000000000000100000000000000000000000000000000000000000000000000000000000000000000000000000000000000000000000000000000000000000000000000000000000000000000000000000000000000000000000000000000000000000000000000000000000000000000000000000000000000000000000000000000000000000000000000000000000000000000000000000000000000000000000000000000000000000000000000000000000000000000000000000000000000000000000000000000000000000000000000000000 /
b100000000000000000000000000000000110000000000000000000000000000000100000000000000000000000000000000000000000000000000000000000000000000000000000000000000000000000000000000000000000000000000000000000000000000000000000000000000000000000000000000000000000000000000000000000000000000000000000000000000000000000000000000000000000000000000000000000000000000000000000000000000000000000000000000000000000000000000000000000000000000000000000000000000000000000000000000000000000000000000000000 ;
b10000 :
b0 8
b1000 9
b10000 >
1)
#180000
b1111 >
0)
0,
#185000
b10001 :
b1 8
b10000 >
1)
#190000
b100011 =
b1111 >
0)
1,
b11 +
b11 -
b11 3
